pynoza/__init__.py
pynoza/from_mathematica.py
pynoza/helpers.py
pynoza/inverse_problem.py
pynoza/solution.c
pynoza/solution.cpython-312-darwin.so
pynoza/solution.py
pynoza-0.3.1.dist-info/LICENSE
pynoza-0.3.1.dist-info/METADATA
pynoza-0.3.1.dist-info/WHEEL
pynoza-0.3.1.dist-info/top_level.txt
pynoza-0.3.1.dist-info/RECORD
