Metadata-Version: 2.1
Name: pynoza
Version: 0.3.1
Summary: Computation of time-domain solutions of Maxwell's equations using the Cartesian multipole expansion
Home-page: https://github.com/eliasleb/pynoza
Author: Elias Le Boudec
Author-email: elias.leboudec@epfl.ch
Project-URL: Bug Tracker, https://github.com/eliasleb/pynoza
Classifier: Programming Language :: Python :: 3
Classifier: License :: OSI Approved :: MIT License
Classifier: Operating System :: OS Independent
Classifier: Programming Language :: Rust
Classifier: Programming Language :: Python :: Implementation :: CPython
Classifier: Programming Language :: Python :: Implementation :: PyPy
Requires-Python: >=3.10, <4
License-File: LICENSE
Requires-Dist: Cython >=0.29.32
Requires-Dist: numpy >=1.21.6
Requires-Dist: matplotlib >=3.5.2
Requires-Dist: pandas >=1.3.5
Requires-Dist: scipy >=1.7.3
Requires-Dist: pytest >=7.1.2
Requires-Dist: sympy >=1.10.1
Requires-Dist: maturin >=0.13.2
Requires-Dist: setuptools >=50
